MANIFEST.in
README.rst
setup.py
tgext/__init__.py
tgext.evolve.egg-info/PKG-INFO
tgext.evolve.egg-info/SOURCES.txt
tgext.evolve.egg-info/dependency_links.txt
tgext.evolve.egg-info/entry_points.txt
tgext.evolve.egg-info/namespace_packages.txt
tgext.evolve.egg-info/not-zip-safe
tgext.evolve.egg-info/pbr.json
tgext.evolve.egg-info/requires.txt
tgext.evolve.egg-info/top_level.txt
tgext/evolve/__init__.py
tgext/evolve/evolver.py
tgext/evolve/ming_evolver.py
tgext/evolve/sqla_evolver.py