Metadata-Version: 1.0
Name: tgext.evolve
Version: 0.0.2
Summary: Manages automatic updates and evolutions which are better suited outside schema migrations
Home-page: https://github.com/axant/tgext.evolve
Author: AXANT
Author-email: tech@axant.it
License: MIT
Keywords: turbogears2.extension
Platform: UNKNOWN
